aldryn_newsblog/__init__.py
aldryn_newsblog/admin.py
aldryn_newsblog/apps.py
aldryn_newsblog/cms_appconfig.py
aldryn_newsblog/cms_apps.py
aldryn_newsblog/cms_menus.py
aldryn_newsblog/cms_plugins.py
aldryn_newsblog/cms_toolbars.py
aldryn_newsblog/cms_wizards.py
aldryn_newsblog/compat.py
aldryn_newsblog/feeds.py
aldryn_newsblog/forms.py
aldryn_newsblog/managers.py
aldryn_newsblog/models.py
aldryn_newsblog/search_indexes.py
aldryn_newsblog/urls.py
aldryn_newsblog/views.py
aldryn_newsblog/boilerplates/bootstrap3/private/img/future.psd
aldryn_newsblog/boilerplates/bootstrap3/private/img/unpublished.psd
aldryn_newsblog/boilerplates/bootstrap3/static/css/aldryn-newsblog/article.css
aldryn_newsblog/boilerplates/bootstrap3/static/img/aldryn_newsblog/future.png
aldryn_newsblog/boilerplates/bootstrap3/static/img/aldryn_newsblog/no-photo.png
aldryn_newsblog/boilerplates/bootstrap3/static/img/aldryn_newsblog/unpublished.png
aldryn_newsblog/boilerplates/bootstrap3/static/js/addons/cl.newsblog.js
aldryn_newsblog/boilerplates/bootstrap3/static/js/libs/jquery.min.js
aldryn_newsblog/boilerplates/bootstrap3/templates/aldryn_newsblog/article_detail.html
aldryn_newsblog/boilerplates/bootstrap3/templates/aldryn_newsblog/article_list.html
aldryn_newsblog/boilerplates/bootstrap3/templates/aldryn_newsblog/base.html
aldryn_newsblog/boilerplates/bootstrap3/templates/aldryn_newsblog/fullwidth.html
aldryn_newsblog/boilerplates/bootstrap3/templates/aldryn_newsblog/two_column.html
aldryn_newsblog/boilerplates/bootstrap3/templates/aldryn_newsblog/includes/article.html
aldryn_newsblog/boilerplates/bootstrap3/templates/aldryn_newsblog/includes/author.html
aldryn_newsblog/boilerplates/bootstrap3/templates/aldryn_newsblog/includes/pagination.html
aldryn_newsblog/boilerplates/bootstrap3/templates/aldryn_newsblog/includes/search_results.html
aldryn_newsblog/boilerplates/bootstrap3/templates/aldryn_newsblog/plugins/archive.html
aldryn_newsblog-2.2.1.dist-info/LICENSE.txt
aldryn_newsblog-2.2.1.dist-info/METADATA
aldryn_newsblog-2.2.1.dist-info/WHEEL
aldryn_newsblog-2.2.1.dist-info/top_level.txt
aldryn_newsblog-2.2.1.dist-info/RECORD
