Metadata-Version: 2.1
Name: aldryn-newsblog
Version: 2.2.1
Summary: Adds blogging and newsing capabilities to django CMS
Home-page: https://github.com/aldryn/aldryn-newsblog
Author: Divio AG
Author-email: info@divio.ch
License: BSD
Platform: UNKNOWN
Classifier: Development Status :: 5 - Production/Stable
Classifier: Environment :: Web Environment
Classifier: Intended Audience :: Developers
Classifier: License :: OSI Approved :: BSD License
Classifier: Operating System :: OS Independent
Classifier: Framework :: Django
Classifier: Framework :: Django :: 1.11
Classifier: Framework :: Django :: 2.0
Classifier: Framework :: Django :: 2.1
Classifier: Programming Language :: Python
Classifier: Programming Language :: Python :: 2
Classifier: Programming Language :: Python :: 2.7
Classifier: Programming Language :: Python :: 3
Classifier: Programming Language :: Python :: 3.4
Classifier: Programming Language :: Python :: 3.5
Classifier: Programming Language :: Python :: 3.6
Classifier: Topic :: Internet :: WWW/HTTP
Classifier: Topic :: Internet :: WWW/HTTP :: Dynamic Content
Classifier: Topic :: Internet :: WWW/HTTP :: Dynamic Content :: News/Diary
Classifier: Topic :: Software Development
Classifier: Topic :: Software Development :: Libraries
Classifier: Topic :: Software Development :: Libraries :: Application Frameworks
Requires-Dist: Django (>=1.11)
Requires-Dist: python-dateutil
Requires-Dist: aldryn-apphooks-config (>=0.5.2)
Requires-Dist: aldryn-boilerplates (>=0.8.0)
Requires-Dist: aldryn-categories (>=1.2.0)
Requires-Dist: aldryn-common (>=1.0.5)
Requires-Dist: aldryn-people (>=2.2.0)
Requires-Dist: aldryn-translation-tools (>=0.3.0)
Requires-Dist: backport-collections (==0.1)
Requires-Dist: django-appdata (>=0.2.1)
Requires-Dist: django-cms (>=3.4.5)
Requires-Dist: djangocms-text-ckeditor (>=3.7.0)
Requires-Dist: django-filer (>=1.4.2)
Requires-Dist: django-parler
Requires-Dist: django-sortedm2m
Requires-Dist: django-taggit (>=0.23.0)
Requires-Dist: lxml
Requires-Dist: pytz
Requires-Dist: six
